aiohttp_asgi/__init__.py
aiohttp_asgi/__main__.py
aiohttp_asgi/py.typed
aiohttp_asgi/resource.py
aiohttp_asgi-0.6.0.dist-info/LICENSE
aiohttp_asgi-0.6.0.dist-info/LICENSE.md
aiohttp_asgi-0.6.0.dist-info/METADATA
aiohttp_asgi-0.6.0.dist-info/WHEEL
aiohttp_asgi-0.6.0.dist-info/entry_points.txt
aiohttp_asgi-0.6.0.dist-info/RECORD
