Metadata-Version: 2.3
Name: aiohttp_asgi
Version: 0.6.0
Summary: Adapter to running ASGI applications on aiohttp
License: Apache-2.0
Keywords: aiohttp,asgi
Author: Dmitry Orlov
Author-email: me@mosquito.su
Requires-Python: >=3.9,<4.0
Classifier: Development Status :: 4 - Beta
Classifier: Intended Audience :: Developers
Classifier: License :: OSI Approved :: Apache Software License
Classifier: Natural Language :: English
Classifier: Operating System :: MacOS
Classifier: Operating System :: Microsoft
Classifier: Operating System :: POSIX
Classifier: Programming Language :: Python
Classifier: Programming Language :: Python :: 3
Classifier: Programming Language :: Python :: 3.9
Classifier: Programming Language :: Python :: 3.10
Classifier: Programming Language :: Python :: 3.11
Classifier: Programming Language :: Python :: 3.12
Classifier: Programming Language :: Python :: 3.13
Classifier: Programming Language :: Python :: 3.7
Classifier: Programming Language :: Python :: 3.8
Classifier: Programming Language :: Python :: Implementation :: CPython
Classifier: Programming Language :: Python :: Implementation :: PyPy
Classifier: Topic :: Internet
Classifier: Topic :: Software Development
Classifier: Topic :: Software Development :: Libraries
Requires-Dist: aiohttp (>=3,<4)
Project-URL: Documentation, https://github.com/mosquito/aiohttp-asgi/blob/master/README.md
Project-URL: Homepage, https://github.com/mosquito/aiohttp-asgi
Project-URL: Source, https://github.com/mosquito/aiohttp-asgi
Project-URL: Tracker, https://github.com/mosquito/aiohttp-asgi/issues
